<?xml version="1.0"?>
<!DOCTYPE hibernate-mapping PUBLIC "-//Hibernate/Hibernate Mapping DTD 3.0//EN"
"http://hibernate.sourceforge.net/hibernate-mapping-3.0.dtd">
<!-- Generated Jul 14, 2011 1:33:55 PM by Hibernate Tools 3.4.0.CR1 -->
<hibernate-mapping>
    <class name="com.cardiodx.db.waban.view.PlateLayoutView" table="PLATE_LAYOUT_VIEW" schema="DNALIMS">
        <composite-id name="id" class="com.cardiodx.db.waban.view.PlateLayoutViewId">
            <key-property name="containerMapId" type="big_decimal">
                <column name="CONTAINER_MAP_ID" precision="22" scale="0" />
            </key-property>
            <key-property name="type" type="string">
                <column name="TYPE" length="20" />
            </key-property>
            <key-property name="containerRows" type="big_decimal">
                <column name="CONTAINER_ROWS" precision="22" scale="0" />
            </key-property>
            <key-property name="containerColumns" type="big_decimal">
                <column name="CONTAINER_COLUMNS" precision="22" scale="0" />
            </key-property>
        </composite-id>
    </class>
</hibernate-mapping>
