<?xml version="1.0"?>
<!DOCTYPE hibernate-mapping PUBLIC "-//Hibernate/Hibernate Mapping DTD 3.0//EN"
"http://hibernate.sourceforge.net/hibernate-mapping-3.0.dtd">
<!-- Generated Jul 14, 2011 12:30:43 PM by Hibernate Tools 3.4.0.CR1 -->
<hibernate-mapping>
    <class name="com.cardiodx.db.waban.table.CaseVariableFldTable" table="CASE_VARIABLE_FLD_TABLE" schema="DNALIMS">
        <comment>Variables or attributes belonging to an accession.</comment>
        <id name="caseVariableFldId" type="big_decimal">
            <column name="CASE_VARIABLE_FLD_ID" precision="22" scale="0" />
            <generator class="assigned" />
        </id>
        <many-to-one name="patient" class="com.cardiodx.db.waban.table.Patient" fetch="select">
            <column name="PATIENT_ID" precision="22" scale="0">
                <comment>Accession identifier and primary key.</comment>
            </column>
        </many-to-one>
        <many-to-one name="organization" class="com.cardiodx.db.waban.table.Organization" fetch="select">
            <column name="ORGANIZATION_ID" precision="22" scale="0">
                <comment>Sponsor company identifier and primary key.</comment>
            </column>
        </many-to-one>
        <many-to-one name="testAccession" class="com.cardiodx.db.waban.table.TestAccession" fetch="select">
            <column name="TEST_ACCESSION_ID" precision="22" scale="0">
                <comment>Test Accession identifier</comment>
            </column>
        </many-to-one>
        <many-to-one name="contact" class="com.cardiodx.db.waban.table.Contact" fetch="select">
            <column name="CONTACT_ID" precision="22" scale="0">
                <comment>Representative identifier and primary key.</comment>
            </column>
        </many-to-one>
        <many-to-one name="protocolDefinedVariable" class="com.cardiodx.db.waban.table.ProtocolDefinedVariable" fetch="select">
            <column name="PROTOCOL_DEFINED_VARIABLE_ID" precision="22" scale="0">
                <comment>Variable identifier and foreign key to the PROTOCOL_DEFINED_VARIABLE table.</comment>
            </column>
        </many-to-one>
        <many-to-one name="subsidiary" class="com.cardiodx.db.waban.table.Subsidiary" fetch="select">
            <column name="SUBSIDIARY_ID" precision="22" scale="0" />
        </many-to-one>
        <property name="value" type="string">
            <column name="VALUE" length="4000">
                <comment>Data for the attribute (male, Hispanic, etc.</comment>
            </column>
        </property>
        <property name="createdBy" type="string">
            <column name="CREATED_BY" length="30">
                <comment>User who created this record.</comment>
            </column>
        </property>
        <property name="dateCreated" type="date">
            <column name="DATE_CREATED" length="7">
                <comment>Date this record was created.</comment>
            </column>
        </property>
        <property name="modifiedBy" type="string">
            <column name="MODIFIED_BY" length="30">
                <comment>User who last modified this record.</comment>
            </column>
        </property>
        <property name="dateModified" type="date">
            <column name="DATE_MODIFIED" length="7">
                <comment>Date this record was last modified.</comment>
            </column>
        </property>
    </class>
</hibernate-mapping>
